[
  {
    "name": "Globo RJ embeddecanais",
    "abrir": "sim",
    "tipo": "player",
    "url": "https://12embeddecanais.xyz/globorj/"
  },
  {
    "name": "Globo SP reidoscanais",
    "abrir": "nao",
    "tipo": "player",
    "url": "https://rdcanais.com/globosp"
  },
  {
    "name": "Globo RJ reidosembed",
    "abrir": "nao",
    "tipo": "player",
    "url": "https://v3.rde.lat/globorj"
  },
  {
    "name": "Globo SP meuplayer",
    "abrir": "sim",
    "tipo": "player",
    "url": "https://meuplayeronlinehd.com/myplay/watch.html?id=globosp"
  },
  {
    "name": "Globo RJ reidoscanais",
    "abrir": "nao",
    "tipo": "player",
    "url": "https://rdcanais.com/globorj"
  },
  {
    "name": "SBT",
    "abrir": "sim",
    "tipo": "m3u8",
    "url": "https://aovivo.maissbt.com/indexMobile.m3u8"
  },
  {
    "name": "Globo RJ sinalpublico",
    "abrir": "nao",
    "tipo": "player",
    "url": "https://sinalpublicoetv.vercel.app/?id=globorj"
  },
  {
    "name": "Globo RJ embedtv",
    "abrir": "nao",
    "tipo": "player",
    "url": "https://ww2.embedtv.lat/globorj"
  },
  {
    "name": "Caze YouTube",
    "abrir": "sim",
    "tipo": "player",
    "url": "https://www.youtube.com/live/OwVHSCdF37g?si=aGhi9X1Auh5yuxPc"
  },
  {
    "name": "Globo SP redecanais",
    "abrir": "nao",
    "tipo": "player",
    "url": "https://redecanaistv.win/player3/ch.php?canal=bobosp"
  }
]


